pytest_cid.py
pytest_cid-1.1.2.dist-info/entry_points.txt
pytest_cid-1.1.2.dist-info/LICENSE
pytest_cid-1.1.2.dist-info/WHEEL
pytest_cid-1.1.2.dist-info/METADATA
pytest_cid-1.1.2.dist-info/RECORD
