Metadata-Version: 2.1
Name: pytest_cid
Version: 1.1.2
Summary: Compare data structures containing matching CIDs of different versions and encoding
Home-page: https://ipfs.io/ipns/12D3KooWEqnTdgqHnkkwarSrJjeMP2ZJiADWLYADaNvUb6SQNyPF/
License: MPL-2.0
Keywords: ipfs storage distribution development
Author: py-ipfs team
Author-email: 
Requires-Python: >=3.5
Classifier: Development Status :: 4 - Beta
Classifier: Intended Audience :: Developers
Classifier: Framework :: Pytest
Classifier: Topic :: Internet
Classifier: Topic :: Scientific/Engineering
Classifier: Topic :: Software Development :: Testing
Classifier: Topic :: System :: Filesystems
Classifier: Topic :: System :: Networking
Classifier: License :: OSI Approved :: Mozilla Public License 2.0 (MPL 2.0)
Classifier: Programming Language :: Python
Classifier: Programming Language :: Python :: 3
Classifier: Programming Language :: Python :: 3 :: Only
Classifier: Programming Language :: Python :: 3.5
Classifier: Programming Language :: Python :: 3.6
Classifier: Programming Language :: Python :: 3.7
Classifier: Programming Language :: Python :: 3.8
Classifier: Programming Language :: Python :: Implementation :: CPython
Classifier: Programming Language :: Python :: Implementation :: PyPy
Classifier: Operating System :: OS Independent
Requires-Dist: pytest >= 5.0, < 7.0
Requires-Dist: py-cid
